geoDL/__init__.py
geoDL/geoDL.py
geoDL-1.0b10.dist-info/LICENSE
geoDL-1.0b10.dist-info/METADATA
geoDL-1.0b10.dist-info/WHEEL
geoDL-1.0b10.dist-info/entry_points.txt
geoDL-1.0b10.dist-info/top_level.txt
geoDL-1.0b10.dist-info/RECORD
