Metadata-Version: 2.1
Name: geoDL
Version: 1.0b10
Summary: Dowload FASTQ files from GEO-NCBI with ease.
Home-page: https://github.com/jduc/geoDL
Author: Julien Duc
Author-email: jduc@protonmail.ch
License: GPL
Keywords: geo ncbi fastq bioinformatic genomic sra
Platform: UNKNOWN
Classifier: Development Status :: 4 - Beta
Classifier: Intended Audience :: Science/Research
Classifier: Topic :: Scientific/Engineering
Classifier: License :: OSI Approved :: GNU General Public License (GPL)
Classifier: Programming Language :: Python :: 2.7
Classifier: Programming Language :: Python :: 3
Requires-Dist: colorama
Requires-Dist: beautifulsoup4
Requires-Dist: six
Requires-Dist: lxml
